aws_super_cli/__init__.py
aws_super_cli/__main__.py
aws_super_cli/aws.py
aws_super_cli/cli.py
aws_super_cli/services/__init__.py
aws_super_cli/services/audit.py
aws_super_cli/services/compute_optimizer.py
aws_super_cli/services/cost.py
aws_super_cli/services/cost_explorer.py
aws_super_cli/services/cost_optimization.py
aws_super_cli/services/ec2.py
aws_super_cli/services/elb.py
aws_super_cli/services/enhanced_reporting.py
aws_super_cli/services/iam.py
aws_super_cli/services/lambda_.py
aws_super_cli/services/rds.py
aws_super_cli/services/report_generator.py
aws_super_cli/services/s3.py
aws_super_cli/services/service_quotas.py
aws_super_cli/services/trusted_advisor.py
aws_super_cli/services/vpc.py
aws_super_cli/utils/__init__.py
aws_super_cli/utils/account_intelligence.py
aws_super_cli/utils/analytics.py
aws_super_cli/utils/arn_intelligence.py
aws_super_cli-0.20.0.dist-info/licenses/LICENSE
tests/__init__.py
tests/test_account_intelligence.py
tests/test_arn_intelligence.py
tests/test_audit.py
tests/test_audit_consistency.py
tests/test_audit_export.py
tests/test_audit_scoring.py
tests/test_cli.py
tests/test_compute_optimizer.py
tests/test_cost_explorer.py
tests/test_cost_optimization_core.py
tests/test_regression.py
tests/test_report_generator.py
tests/test_service_quotas.py
tests/test_trusted_advisor.py
tests/test_version_consistency.py
aws_super_cli-0.20.0.dist-info/METADATA
aws_super_cli-0.20.0.dist-info/WHEEL
aws_super_cli-0.20.0.dist-info/entry_points.txt
aws_super_cli-0.20.0.dist-info/top_level.txt
aws_super_cli-0.20.0.dist-info/RECORD
