Metadata-Version: 2.4
Name: aws-super-cli
Version: 0.20.0
Summary: AWS Super CLI - Multi-account AWS resource discovery with service-level cost intelligence
Home-page: https://github.com/marceloacosta/aws-super-cli
Author: Marcelo Acosta
Author-email: marcelo.acosta@latintradegroup.com
Project-URL: Bug Reports, https://github.com/marceloacosta/aws-super-cli/issues
Project-URL: Source, https://github.com/marceloacosta/aws-super-cli
Keywords: aws,cli,multi-account,devops,cloud,infrastructure
Classifier: Development Status :: 4 - Beta
Classifier: Intended Audience :: Developers
Classifier: Intended Audience :: System Administrators
Classifier: Topic :: System :: Systems Administration
Classifier: Topic :: Utilities
Classifier: License :: OSI Approved :: Apache Software License
Classifier: Programming Language :: Python :: 3
Classifier: Programming Language :: Python :: 3.8
Classifier: Programming Language :: Python :: 3.9
Classifier: Programming Language :: Python :: 3.10
Classifier: Programming Language :: Python :: 3.11
Classifier: Programming Language :: Python :: 3.12
Classifier: Operating System :: OS Independent
Requires-Python: >=3.8
License-File: LICENSE
Requires-Dist: boto3>=1.26.0
Requires-Dist: aioboto3>=11.0.0
Requires-Dist: typer>=0.7.0
Requires-Dist: rich>=13.0.0
Requires-Dist: botocore>=1.29.0
Requires-Dist: aiohttp>=3.8.0
Dynamic: author
Dynamic: author-email
Dynamic: classifier
Dynamic: description
Dynamic: description-content-type
Dynamic: home-page
Dynamic: keywords
Dynamic: license-file
Dynamic: project-url
Dynamic: requires-dist
Dynamic: requires-python
Dynamic: summary
